pygrowcube/__init__.py
pygrowcube/cli.py
pygrowcube/message.py
pygrowcube/messageclient.py
pygrowcube/pygrowcube.py
pygrowcube/timeouthelper.py
pygrowcube-0.2.0.dist-info/AUTHORS.rst
pygrowcube-0.2.0.dist-info/LICENSE
pygrowcube-0.2.0.dist-info/METADATA
pygrowcube-0.2.0.dist-info/WHEEL
pygrowcube-0.2.0.dist-info/entry_points.txt
pygrowcube-0.2.0.dist-info/top_level.txt
pygrowcube-0.2.0.dist-info/RECORD
