Metadata-Version: 2.1
Name: pygrowcube
Version: 0.2.0
Summary: Python modules for interacting with Elecrow GrowCube smart plant watering system
Home-page: https://github.com/robotedward/pygrowcube
Author: Edward Fretwell
Author-email: pypi@comfortableshoe.co.uk
License: MIT license
Keywords: pygrowcube
Classifier: Development Status :: 2 - Pre-Alpha
Classifier: Intended Audience :: Developers
Classifier: License :: OSI Approved :: MIT License
Classifier: Natural Language :: English
Classifier: Programming Language :: Python :: 3
Classifier: Programming Language :: Python :: 3.6
Classifier: Programming Language :: Python :: 3.7
Classifier: Programming Language :: Python :: 3.8
Requires-Python: >=3.6
License-File: LICENSE
License-File: AUTHORS.rst
Requires-Dist: Click (>=7.0)
